{"days": [[" ", " ", "NULL", "NULL", "NULL", " ", "NULL", " ", " ", "NULL", " ", "NULL", " ", " ", " ", " ", "NULL", "NULL", "NULL", "NULL", "NULL", " ", " ", " ", " ", "NULL", "NULL", " ", " ", "NULL", " "], [" ", " ", "NULL", "NULL", " ", "NULL", " ", "NULL", "NULL", " ", "NULL", " ", "NULL", " ", " ", " ", "NULL", " ", "NULL", " ", " ", "NULL", " ", " ", "NULL", "NULL", "NULL", " ", " ", " ", "NULL"], [" ", " ", " ", "NULL", "NULL", " ", "NULL", " ", " ", "NULL", " ", " ", " ", " ", " ", " ", "NULL", "NULL", " ", " ", "NULL", "NULL", " ", " ", " ", "NULL", "NULL", "NULL", "NULL", "NULL", " "], ["NULL", " ", "NULL", "NULL", " ", "NULL", " ", " ", " ", "NULL", " ", "NULL", "NULL", " ", " ", "NULL", "NULL", " ", " ", " ", "NULL", " ", "NULL", "NULL", " ", "NULL", " ", " ", "NULL", "NULL", "NULL"], ["NULL", "NULL", "NULL", "NULL", "NULL", "NULL", "NULL", " ", " ", "NULL", " ", "NULL", "NULL", " ", " ", "NULL", "NULL", "NULL", " ", "NULL", " ", "NULL", " ", " ", " ", "NULL", "NULL", " ", " ", " ", "NULL"], ["NULL", "NULL", "NULL", " ", "NULL", "NULL", " ", "NULL", " ", "NULL", "NULL", "NULL", "NULL", " ", "NULL", "NULL", " ", "NULL", "NULL", "NULL", "NULL", "NULL", "NULL", "NULL", " ", " ", " ", "NULL", "NULL", "NULL", " "], ["NULL", " ", "NULL", " ", " ", "NULL", " ", " ", "NULL", " ", " ", "NULL", " ", "NULL", " ", "NULL", " ", " ", "NULL", "NULL", " ", "NULL", " ", "NULL", " ", " ", "NULL", "NULL", " ", " ", " "]], "major": ["Economics", "English", "Art", "Nursing"], "maj": "Economics,English,Art,Nursing", "minor": [], "min": "", "yearsWorked": "0", "hoursPer": "5", "first": "Alicia", "last": "Gray", "username": "1ccea99d-bb95-4675-9c49-a0091d477a7b", "password": "test", "userID": "1ccea99d-bb95-4675-9c49-a0091d477a7b", "director": false, "numberOfShifts": 0}