{"days": [[" ", " ", "NULL", " ", " ", "NULL", " ", "NULL", " ", "NULL", "NULL", "NULL", "NULL", "NULL", "NULL", " ", "NULL", " ", "NULL", "NULL", "NULL", " ", " ", "NULL", " ", " ", "NULL", " ", " ", " ", "NULL"], [" ", " ", "NULL", " ", " ", "NULL", " ", "NULL", " ", " ", "NULL", "NULL", " ", "NULL", "NULL", "NULL", "NULL", " ", " ", "NULL", " ", "NULL", " ", "NULL", " ", "NULL", "NULL", " ", " ", " ", "NULL"], [" ", " ", " ", "NULL", "NULL", " ", " ", " ", "NULL", "NULL", " ", "NULL", " ", " ", " ", "NULL", " ", " ", " ", " ", " ", "NULL", " ", " ", " ", " ", " ", " ", " ", " ", "NULL"], ["NULL", "NULL", "NULL", "NULL", "NULL", "NULL", " ", "NULL", "NULL", "NULL", "NULL", " ", " ", "NULL", " ", " ", " ", "NULL", " ", " ", " ", " ", "NULL", "NULL", " ", " ", " ", "NULL", " ", "NULL", " "], [" ", " ", "NULL", "NULL", " ", "NULL", "NULL", " ", "NULL", "NULL", "NULL", "NULL", " ", "NULL", "NULL", " ", "NULL", " ", "NULL", "NULL", " ", "NULL", "NULL", "NULL", " ", "NULL", "NULL", " ", " ", " ", "NULL"], [" ", " ", " ", " ", " ", "NULL", "NULL", " ", " ", "NULL", "NULL", "NULL", " ", "NULL", "NULL", " ", "NULL", "NULL", "NULL", " ", "NULL", "NULL", "NULL", "NULL", " ", " ", " ", " ", " ", " ", " "], ["NULL", "NULL", "NULL", "NULL", "NULL", " ", " ", "NULL", "NULL", " ", " ", "NULL", " ", "NULL", " ", "NULL", " ", "NULL", " ", "NULL", "NULL", "NULL", " ", "NULL", " ", " ", "NULL", "NULL", " ", "NULL", " "]], "major": ["Pre-Professional Programs", "Business Administration", "Spanish", "Creative Writing"], "maj": "Pre-Professional Programs,Business Administration,Spanish,Creative Writing", "minor": [], "min": "", "yearsWorked": "2", "hoursPer": "5", "first": "David", "last": "Flores", "username": "DavidFlores", "password": "test", "userID": "5d2321c9-ddbd-49f2-8c53-41cb8826f381", "director": false}