{"days": [[" ", "NULL", "NULL", "NULL", " ", "NULL", " ", " ", " ", "NULL", "NULL", "NULL", " ", "NULL", " ", "NULL", " ", " ", " ", " ", " ", "NULL", "NULL", "NULL", "NULL", " ", " ", " ", "NULL", "NULL", "NULL"], ["NULL", " ", "NULL", " ", "NULL", "NULL", "NULL", "NULL", "NULL", " ", "NULL", "NULL", "NULL", "NULL", "NULL", "NULL", "NULL", " ", "NULL", " ", " ", "NULL", " ", "NULL", " ", "NULL", " ", "NULL", " ", " ", "NULL"], [" ", " ", " ", "NULL", "NULL", "NULL", "NULL", "NULL", "NULL", "NULL", "NULL", " ", "NULL", " ", "NULL", " ", "NULL", " ", " ", " ", " ", " ", " ", "NULL", " ", " ", " ", "NULL", " ", " ", "NULL"], ["NULL", "NULL", "NULL", "NULL", " ", " ", " ", " ", "NULL", "NULL", "NULL", "NULL", "NULL", " ", "NULL", " ", "NULL", " ", " ", " ", "NULL", " ", "NULL", " ", "NULL", " ", "NULL", "NULL", " ", "NULL", " "], [" ", " ", " ", "NULL", " ", " ", " ", " ", "NULL", "NULL", " ", " ", "NULL", "NULL", "NULL", "NULL", " ", " ", "NULL", "NULL", "NULL", "NULL", "NULL", "NULL", " ", " ", "NULL", "NULL", "NULL", "NULL", " "], ["NULL", " ", "NULL", "NULL", " ", "NULL", "NULL", "NULL", "NULL", "NULL", "NULL", "NULL", " ", " ", " ", " ", " ", " ", " ", " ", " ", "NULL", "NULL", " ", " ", " ", "NULL", "NULL", " ", " ", "NULL"], [" ", " ", "NULL", "NULL", "NULL", " ", " ", "NULL", " ", "NULL", "NULL", "NULL", "NULL", " ", " ", " ", "NULL", " ", " ", "NULL", " ", "NULL", " ", " ", " ", "NULL", "NULL", " ", "NULL", "NULL", "NULL"]], "major": ["Pre-Engineering"], "maj": "Pre-Engineering", "minor": ["Interdisciplinary Studies", "Neuroscience", "Business Administration", "English as a Second Language - ESL"], "min": "Interdisciplinary Studies,Neuroscience,Business Administration,English as a Second Language - ESL", "yearsWorked": "4", "hoursPer": "9", "first": "Monica", "last": "Bishop", "username": "MonicaBishop", "password": "test", "userID": "74a90e7d-588e-4de8-af79-edc39ccedd84", "director": false}